blobkeeper/__init__.py
blobkeeper/data.py
blobkeeper/index.py
blobkeeper/types.py
blobkeeper-0.0.2.dist-info/LICENSE
blobkeeper-0.0.2.dist-info/METADATA
blobkeeper-0.0.2.dist-info/WHEEL
blobkeeper-0.0.2.dist-info/top_level.txt
blobkeeper-0.0.2.dist-info/RECORD
