Metadata-Version: 2.1
Name: blobkeeper
Version: 0.0.2
Summary: A Python package for storing and managing binary data blobs.
Author-email: Kirill Orlov <IDDT@users.noreply.github.com>
License: MIT License
Project-URL: Homepage, https://github.com/IDDT/blobkeeper
Project-URL: Repository, https://github.com/IDDT/blobkeeper.git
Classifier: Development Status :: 3 - Alpha
Classifier: Intended Audience :: Developers
Classifier: License :: OSI Approved :: MIT License
Classifier: Programming Language :: Python :: 3
Classifier: Programming Language :: Python :: 3.8
Classifier: Programming Language :: Python :: 3.9
Classifier: Programming Language :: Python :: 3.10
Classifier: Programming Language :: Python :: 3.11
Requires-Python: >=3.9
License-File: LICENSE
